{
  "$schema": "https://developer.microsoft.com/json-schemas/fabric/item/report/definition/visualContainer/2.1.0/schema.json",
  "name": "456b10b07680051136db",
  "position": {
    "x": 0,
    "y": 2.2222222222222223,
    "z": 1000,
    "height": 135.55555555555554,
    "width": 220,
    "tabOrder": 1000
  },
  "visual": {
    "visualType": "areaChart",
    "query": {
      "queryState": {
        "Category": {
          "projections": [
            {
              "field": {
                "Column": {
                  "Expression": {
                    "SourceRef": {
                      "Entity": "Calendrier_auto"
                    }
                  },
                  "Property": "Mois"
                }
              },
              "queryRef": "Calendrier_auto.Mois",
              "nativeQueryRef": "Mois",
              "active": true
            }
          ]
        },
        "Y": {
          "projections": [
            {
              "field": {
                "Measure": {
                  "Expression": {
                    "SourceRef": {
                      "Entity": "mesures"
                    }
                  },
                  "Property": "CA"
                }
              },
              "queryRef": "mesures.CA",
              "nativeQueryRef": "CA"
            }
          ]
        }
      },
      "sortDefinition": {
        "sort": [
          {
            "field": {
              "Measure": {
                "Expression": {
                  "SourceRef": {
                    "Entity": "mesures"
                  }
                },
                "Property": "CA"
              }
            },
            "direction": "Descending"
          }
        ],
        "isDefaultSort": true
      },
      "options": {
        "allowBinnedLineSample": true
      }
    },
    "objects": {
      "lineStyles": [
        {
          "properties": {
            "lineChartType": {
              "expr": {
                "Literal": {
                  "Value": "'smooth'"
                }
              }
            },
            "strokeWidth": {
              "expr": {
                "Literal": {
                  "Value": "1D"
                }
              }
            },
            "showMarker": {
              "expr": {
                "Literal": {
                  "Value": "false"
                }
              }
            },
            "markerShape": {
              "expr": {
                "Literal": {
                  "Value": "'diamond'"
                }
              }
            },
            "markerSize": {
              "expr": {
                "Literal": {
                  "Value": "3D"
                }
              }
            },
            "strokeShow": {
              "expr": {
                "Literal": {
                  "Value": "true"
                }
              }
            },
            "lineStyle": {
              "expr": {
                "Literal": {
                  "Value": "'solid'"
                }
              }
            },
            "areaShow": {
              "expr": {
                "Literal": {
                  "Value": "true"
                }
              }
            },
            "strokeTransparency": {
              "expr": {
                "Literal": {
                  "Value": "20D"
                }
              }
            }
          }
        },
        {
          "properties": {
            "lineStyle": {
              "expr": {
                "Literal": {
                  "Value": "'dotted'"
                }
              }
            }
          },
          "selector": {
            "data": [
              {
                "scopeId": {
                  "Comparison": {
                    "ComparisonKind": 0,
                    "Left": {
                      "Column": {
                        "Expression": {
                          "SourceRef": {
                            "Entity": "Time Intelligence"
                          }
                        },
                        "Property": "Time calculation"
                      }
                    },
                    "Right": {
                      "Literal": {
                        "Value": "'LY'"
                      }
                    }
                  }
                }
              }
            ]
          }
        }
      ],
      "categoryAxis": [
        {
          "properties": {
            "showAxisTitle": {
              "expr": {
                "Literal": {
                  "Value": "false"
                }
              }
            },
            "show": {
              "expr": {
                "Literal": {
                  "Value": "false"
                }
              }
            },
            "preferredCategoryWidth": {
              "expr": {
                "Literal": {
                  "Value": "20D"
                }
              }
            },
            "axisType": {
              "expr": {
                "Literal": {
                  "Value": "'Scalar'"
                }
              }
            },
            "start": {
              "expr": {
                "Literal": {
                  "Value": "0D"
                }
              }
            },
            "end": {
              "expr": {
                "Literal": {
                  "Value": "12D"
                }
              }
            }
          }
        }
      ],
      "valueAxis": [
        {
          "properties": {
            "showAxisTitle": {
              "expr": {
                "Literal": {
                  "Value": "false"
                }
              }
            },
            "show": {
              "expr": {
                "Literal": {
                  "Value": "false"
                }
              }
            }
          }
        }
      ],
      "dataPoint": [
        {
          "properties": {
            "fill": {
              "solid": {
                "color": {
                  "expr": {
                    "ThemeDataColor": {
                      "ColorId": 3,
                      "Percent": -0.25
                    }
                  }
                }
              }
            }
          },
          "selector": {
            "metadata": "mesures.CA"
          }
        },
        {
          "properties": {
            "transparency": {
              "expr": {
                "Literal": {
                  "Value": "90D"
                }
              }
            }
          }
        },
        {
          "properties": {
            "fill": {
              "solid": {
                "color": {
                  "expr": {
                    "ThemeDataColor": {
                      "ColorId": 6,
                      "Percent": -0.25
                    }
                  }
                }
              }
            }
          },
          "selector": {
            "metadata": "mesures.Nbre Commande"
          }
        }
      ]
    },
    "visualContainerObjects": {
      "background": [
        {
          "properties": {
            "show": {
              "expr": {
                "Literal": {
                  "Value": "false"
                }
              }
            }
          }
        }
      ],
      "border": [
        {
          "properties": {
            "show": {
              "expr": {
                "Literal": {
                  "Value": "false"
                }
              }
            }
          }
        }
      ],
      "visualHeader": [
        {
          "properties": {
            "show": {
              "expr": {
                "Literal": {
                  "Value": "false"
                }
              }
            }
          }
        }
      ],
      "title": [
        {
          "properties": {
            "show": {
              "expr": {
                "Literal": {
                  "Value": "false"
                }
              }
            }
          }
        }
      ],
      "padding": [
        {
          "properties": {
            "left": {
              "expr": {
                "Literal": {
                  "Value": "0D"
                }
              }
            },
            "right": {
              "expr": {
                "Literal": {
                  "Value": "0D"
                }
              }
            }
          }
        }
      ],
      "lockAspect": [
        {
          "properties": {
            "show": {
              "expr": {
                "Literal": {
                  "Value": "true"
                }
              }
            }
          }
        }
      ],
      "visualTooltip": [
        {
          "properties": {
            "show": {
              "expr": {
                "Literal": {
                  "Value": "false"
                }
              }
            }
          }
        }
      ]
    },
    "drillFilterOtherVisuals": true
  },
  "parentGroupName": "08664e9d271ac8b30157"
}